hyx/__init__.py
hyx-0.0.1.dist-info/METADATA
hyx-0.0.1.dist-info/WHEEL
hyx-0.0.1.dist-info/RECORD
